README.md
setup.py
aior/__init__.py
aior/__main__.py
aior/application.py
aior/constants.py
aior/docs.py
aior/helpers.py
aior/log.py
aior/typedefs.py
aior/utils.py
aior.egg-info/PKG-INFO
aior.egg-info/SOURCES.txt
aior.egg-info/dependency_links.txt
aior.egg-info/requires.txt
aior.egg-info/top_level.txt
aior/components/__init__.py
aior/components/dao.py
aior/components/http_exceptions.py
aior/components/http_handler.py
aior/components/http_status.py
aior/components/stdin_handler.py
aior/components/ws_exceptions.py
aior/components/ws_handlers.py