Metadata-Version: 1.2
Name: aior
Version: 1.0.1
Summary: Aior is a async, fast server/client framework based on aiohttp, which provides many out-of-box components for quickly developing restful http api and so on.
Home-page: https://github.com/Dephin/aior
Author: Dephin
Author-email: 
License: MIT License
Platform: UNKNOWN
Requires-Python: >=3.7
